RocketSniff/__init__.py
RocketSniff/cli.py
RocketSniff/core.py
rocketsniff-1.1.0.dist-info/METADATA
rocketsniff-1.1.0.dist-info/WHEEL
rocketsniff-1.1.0.dist-info/entry_points.txt
rocketsniff-1.1.0.dist-info/top_level.txt
rocketsniff-1.1.0.dist-info/RECORD
