Metadata-Version: 2.4
Name: rocketsniff
Version: 1.1.0
Summary: Python module to find Rocket League server IP and port from logs
Author: Your Name
Requires-Python: >=3.8
Dynamic: author
Dynamic: requires-python
Dynamic: summary
